sfini/__init__.py
sfini/_cli.py
sfini/_util.py
sfini/activity.py
sfini/state_machine.py
sfini/task_resource.py
sfini/worker.py
sfini/execution/__init__.py
sfini/execution/_execution.py
sfini/execution/history.py
sfini/state/__init__.py
sfini/state/_base.py
sfini/state/_state.py
sfini/state/choice.py
sfini-0.1.0.dist-info/LICENSE
sfini-0.1.0.dist-info/METADATA
sfini-0.1.0.dist-info/WHEEL
sfini-0.1.0.dist-info/top_level.txt
sfini-0.1.0.dist-info/RECORD
