Metadata-Version: 2.1
Name: sfini
Version: 0.1.0
Summary: Create, run and manage AWS Step Functions easily
Home-page: https://github.com/EpicWink/sfini
Author: Laurie
Author-email: laurie@sitesee.com.au
Maintainer: Laurie
Maintainer-email: laurie@sitesee.com.au
License: MIT
Project-URL: Documentation, https://sfini.readthedocs.io/en/latest/
Project-URL: Source, https://github.com/EpicWink/sfini
Project-URL: Bugs, https://github.com/EpicWink/sfini/issues
Keywords: aws sfn service step functions states
Platform: UNKNOWN
Classifier: Environment :: Console
Classifier: Intended Audience :: Developers
Classifier: Programming Language :: Python :: 3 :: Only
Classifier: Natural Language :: English
Classifier: Operating System :: POSIX :: Linux
Classifier: Operating System :: Microsoft :: Windows
Classifier: Operating System :: MacOS
Classifier: License :: OSI Approved :: MIT License
Requires-Python: ~=3.6
Requires-Dist: boto3
Provides-Extra: dev
Requires-Dist: moto ; extra == 'dev'
Requires-Dist: pytest ; extra == 'dev'
Requires-Dist: pytest-cov ; extra == 'dev'
Requires-Dist: pytest-timeout ; extra == 'dev'
Requires-Dist: sphinx ; extra == 'dev'
Requires-Dist: sphinx-rtd-theme ; extra == 'dev'
